odoo8_addon_l10n_it_fatturapa_out_wt-8.0.2.0.0-nspkg.pth
odoo_addons/l10n_it_fatturapa_out_wt/README.rst
odoo_addons/l10n_it_fatturapa_out_wt/__init__.py
odoo_addons/l10n_it_fatturapa_out_wt/__openerp__.py
odoo_addons/l10n_it_fatturapa_out_wt/i18n/l10n_it_fatturapa_out_wt.pot
odoo_addons/l10n_it_fatturapa_out_wt/readme/CONTRIBUTORS.rst
odoo_addons/l10n_it_fatturapa_out_wt/readme/DESCRIPTION.rst
odoo_addons/l10n_it_fatturapa_out_wt/static/description/icon.png
odoo_addons/l10n_it_fatturapa_out_wt/static/description/index.html
odoo_addons/l10n_it_fatturapa_out_wt/tests/__init__.py
odoo_addons/l10n_it_fatturapa_out_wt/tests/test_fatturapa_wt.py
odoo_addons/l10n_it_fatturapa_out_wt/tests/data/IT06363391001_00011.xml
odoo_addons/l10n_it_fatturapa_out_wt/tests/data/IT06363391001_00014.xml
odoo_addons/l10n_it_fatturapa_out_wt/tests/data/IT06363391001_00015.xml
odoo_addons/l10n_it_fatturapa_out_wt/tests/data/IT06363391001_00016.xml
odoo_addons/l10n_it_fatturapa_out_wt/tests/data/IT06363391001_00017.xml
odoo_addons/l10n_it_fatturapa_out_wt/tests/data/IT06363391001_00018.xml
odoo_addons/l10n_it_fatturapa_out_wt/tests/data/IT06363391001_00019.xml
odoo_addons/l10n_it_fatturapa_out_wt/wizard/__init__.py
odoo_addons/l10n_it_fatturapa_out_wt/wizard/wizard_export_fatturapa.py
odoo8_addon_l10n_it_fatturapa_out_wt-8.0.2.0.0.dist-info/METADATA
odoo8_addon_l10n_it_fatturapa_out_wt-8.0.2.0.0.dist-info/WHEEL
odoo8_addon_l10n_it_fatturapa_out_wt-8.0.2.0.0.dist-info/namespace_packages.txt
odoo8_addon_l10n_it_fatturapa_out_wt-8.0.2.0.0.dist-info/top_level.txt
odoo8_addon_l10n_it_fatturapa_out_wt-8.0.2.0.0.dist-info/RECORD
